tinyvote/__init__.py
tinyvote/tinyvote.py
tinyvote-0.1.2.dist-info/LICENSE
tinyvote-0.1.2.dist-info/METADATA
tinyvote-0.1.2.dist-info/WHEEL
tinyvote-0.1.2.dist-info/top_level.txt
tinyvote-0.1.2.dist-info/RECORD
