Metadata-Version: 2.1
Name: tinyvote
Version: 0.1.2
Summary: Minimal pure-Python library that demonstrates a basic encrypted voting workflow by leveraging a secure multi-party computation (MPC) protocol.
Author: Choose K
Author-email: team@choosek.com
License: MIT
Project-URL: Repository, https://github.com/choosek/tinyvote
Project-URL: Documentation, https://tinyvote.readthedocs.io
Requires-Python: >=3.7
License-File: LICENSE
Requires-Dist: modulo ~=2.1
Requires-Dist: tinynmc ~=0.2
Provides-Extra: coveralls
Requires-Dist: coveralls ~=3.3.1 ; extra == 'coveralls'
Provides-Extra: docs
Requires-Dist: toml ~=0.10.2 ; extra == 'docs'
Requires-Dist: sphinx ~=5.3.0 ; extra == 'docs'
Requires-Dist: sphinx-rtd-theme ~=1.0.0 ; extra == 'docs'
Requires-Dist: sphinx-autodoc-typehints ~=1.12.0 ; extra == 'docs'
Provides-Extra: lint
Requires-Dist: pylint ~=2.17.0 ; extra == 'lint'
Provides-Extra: publish
Requires-Dist: build ~=0.10 ; extra == 'publish'
Requires-Dist: twine ~=4.0 ; extra == 'publish'
Provides-Extra: test
Requires-Dist: pytest ~=7.2 ; extra == 'test'
Requires-Dist: pytest-cov ~=4.0 ; extra == 'test'
